lektor_webdav.py
lektor_webdav-0.1.1.post5.dist-info/METADATA
lektor_webdav-0.1.1.post5.dist-info/RECORD
lektor_webdav-0.1.1.post5.dist-info/WHEEL
lektor_webdav-0.1.1.post5.dist-info/entry_points.txt
lektor_webdav-0.1.1.post5.dist-info/top_level.txt
