Metadata-Version: 2.1
Name: lektor-webdav
Version: 0.1.1.post5
Summary: Lektor plugin to get a list of files from a WebDAV server
Home-page: https://github.com/mesbahamin/lektor-webdav
Author: Amin Mesbah
Author-email: dev@aminmesbah.com
License: MIT
Project-URL: Source, https://github.com/mesbahamin/lektor-webdav
Project-URL: Tracker, https://github.com/mesbahamin/lektor-webdav/issues
Keywords: lektor webdav blog website files plugin
Platform: UNKNOWN
Classifier: Development Status :: 3 - Alpha
Classifier: Environment :: Plugins
Classifier: Framework :: Lektor
Classifier: License :: OSI Approved :: MIT License
Requires-Dist: requests
